__init__.py
app.py
app_local.py
gunicorn_config.py
sampling.py
assets/__init__.py
components/__init__.py
components/footer.py
components/login.py
components/navbar.py
pages/__init__.py
pages/home.py
pages/login.py
pages/logout.py
pages/not_found_404.py
pages/register.py
pages/annotate/__init__.py
pages/annotate/callbacks.py
pages/annotate/layout.py
pages/annotate/model.py
pages/annotate/sampling.py
pages/compare/__init__.py
pages/compare/layout.py
pages/project/__init__.py
pages/project/callbacks.py
pages/project/layout.py
pages/visualize/__init__.py
pages/visualize/layout.py
utils/__init__.py
utils/auth.py
utils/settings.py
utils/utils.py
yapat-0.1.0a0.dist-info/LICENSE
yapat-0.1.0a0.dist-info/METADATA
yapat-0.1.0a0.dist-info/WHEEL
yapat-0.1.0a0.dist-info/top_level.txt
yapat-0.1.0a0.dist-info/RECORD
